test2_z/__init__.py
test2_z/core.py
test2_z-0.1.1.dist-info/METADATA
test2_z-0.1.1.dist-info/WHEEL
test2_z-0.1.1.dist-info/top_level.txt
test2_z-0.1.1.dist-info/RECORD
